buiz/__init__.py
buiz/main.py
buiz/question.py
buiz-0.1.dist-info/LICENSE
buiz-0.1.dist-info/METADATA
buiz-0.1.dist-info/WHEEL
buiz-0.1.dist-info/top_level.txt
buiz-0.1.dist-info/RECORD
